numtofi/__init__.py
numtofi/cli.py
numtofi/core.py
tests/__init__.py
tests/test_core.py
numtofi-0.8.dist-info/LICENSE
numtofi-0.8.dist-info/METADATA
numtofi-0.8.dist-info/WHEEL
numtofi-0.8.dist-info/entry_points.txt
numtofi-0.8.dist-info/top_level.txt
numtofi-0.8.dist-info/RECORD
