Metadata-Version: 2.1
Name: numtofi
Version: 0.8
Summary: A package to convert numbers to Finnish textual representation
Home-page: https://github.com/markomanninen/numtofi
Author: Marko T. Manninen
Author-email: elonmedia@gmail.com
License-File: LICENSE
